genaiterminal/__init__.py
genaiterminal/config.py
genaiterminal/generate_code.py
genaiterminal-0.1.0.dist-info/METADATA
genaiterminal-0.1.0.dist-info/WHEEL
genaiterminal-0.1.0.dist-info/top_level.txt
genaiterminal-0.1.0.dist-info/RECORD
