Metadata-Version: 2.1
Name: genaiterminal
Version: 0.1.0
Summary: AI code generation package
Home-page: UNKNOWN
Author: Anubhav Mazumder
Author-email: terminalishere127@gmail.com
License: UNKNOWN
Platform: UNKNOWN
Requires-Dist: google-generativeai
